vmc_reporter/__init__.py
vmc_reporter/__version__.py
vmc_reporter/py.typed
vmc_reporter-2.0.8.dist-info/METADATA
vmc_reporter-2.0.8.dist-info/WHEEL
vmc_reporter-2.0.8.dist-info/top_level.txt
vmc_reporter-2.0.8.dist-info/RECORD
