Metadata-Version: 2.1
Name: vmc-reporter
Version: 2.0.8
Summary: vmc-reporter - A python package for reporting scanner findings to VMC
Home-page: 
Author: Olivier Favre
Author-email: olivier.favre@sbb.ch
Classifier: Development Status :: 4 - Beta
Classifier: Intended Audience :: Developers
Classifier: Programming Language :: Python :: 3.10
Requires-Python: >=3.10.*
Requires-Dist: requests
Requires-Dist: jsonschema
Requires-Dist: packaging
